macaw/__init__.py
macaw/dictionary.txt
macaw/macaw.py
macawspeak-0.1.3.dist-info/LICENSE
macawspeak-0.1.3.dist-info/METADATA
macawspeak-0.1.3.dist-info/WHEEL
macawspeak-0.1.3.dist-info/entry_points.txt
macawspeak-0.1.3.dist-info/top_level.txt
macawspeak-0.1.3.dist-info/RECORD
