Metadata-Version: 2.1
Name: macawspeak
Version: 0.1.3
Summary: Better password generation inspired by our colorful, feathered friends.
Home-page: https://github.com/dcchambers/macaw
Author: Dakota Chambers
Author-email: dakotachambers@gmail.com
License: UNKNOWN
Keywords: password,macaw
Platform: UNKNOWN
Classifier: Programming Language :: Python :: 3
Classifier: License :: OSI Approved :: MIT License
Classifier: Operating System :: OS Independent
